nomad_camels_extension_eLabFTW/__init__.py
nomad_camels_extension_eLabFTW/elabFTW_extension.py
nomad_camels_extension_eLabFTW/elab_communication.py
nomad_camels_extension_elabftw-0.1.5.dist-info/licenses/LICENSE.txt
nomad_camels_extension_elabftw-0.1.5.dist-info/METADATA
nomad_camels_extension_elabftw-0.1.5.dist-info/WHEEL
nomad_camels_extension_elabftw-0.1.5.dist-info/top_level.txt
nomad_camels_extension_elabftw-0.1.5.dist-info/RECORD
