Metadata-Version: 2.4
Name: nomad_camels_extension_eLabFTW
Version: 0.1.5
Summary: Extension for communication with eLabFTW
Author-email: FAIRmat - HU Berlin <nomad-camels@fau.de>
Project-URL: GitHub Page, https://github.com/FAU-LAP/CAMELS_extensions
Project-URL: GitHub NOMAD CAMELS, https://github.com/FAU-LAP/NOMAD-CAMELS
Classifier: Programming Language :: Python :: 3
Classifier: License :: OSI Approved :: GNU Lesser General Public License v2 (LGPLv2)
Requires-Python: >=3.11.3
License-File: LICENSE.txt
Requires-Dist: nomad-camels>=1.4.2
Requires-Dist: elabapi-python>=5.0.0
Dynamic: license-file
